wikimarkup/__init__.py
wikimarkup/entities.py
wikimarkup/parser.py
py_wikimarkup-2.3.0.dist-info/LICENSE
py_wikimarkup-2.3.0.dist-info/METADATA
py_wikimarkup-2.3.0.dist-info/WHEEL
py_wikimarkup-2.3.0.dist-info/top_level.txt
py_wikimarkup-2.3.0.dist-info/RECORD
