Metadata-Version: 2.1
Name: py-wikimarkup
Version: 2.3.0
Summary: A basic MediaWiki markup parser.
Home-page: http://www.github.com/dgilman/py-wikimarkup/
Author: David Cramer
Author-email: dcramer@gmail.com
Classifier: Development Status :: 6 - Mature
Classifier: License :: OSI Approved :: GNU General Public License v3 or later (GPLv3+)
Classifier: Programming Language :: Python :: 3 :: Only
Requires-Python: >=3.7
License-File: LICENSE
